cadence_example_plugins/__init__.py
cadence_example_plugins/math_agent/__init__.py
cadence_example_plugins/math_agent/agent.py
cadence_example_plugins/math_agent/plugin.py
cadence_example_plugins/math_agent/tools.py
cadence_example_plugins/myinfo_agent/__init__.py
cadence_example_plugins/myinfo_agent/agent.py
cadence_example_plugins/myinfo_agent/plugin.py
cadence_example_plugins/myinfo_agent/tools.py
cadence_example_plugins/search_agent/__init__.py
cadence_example_plugins/search_agent/agent.py
cadence_example_plugins/search_agent/plugin.py
cadence_example_plugins/search_agent/tools.py
cadence_example_plugins-1.3.0.dist-info/LICENSE
cadence_example_plugins-1.3.0.dist-info/METADATA
cadence_example_plugins-1.3.0.dist-info/WHEEL
cadence_example_plugins-1.3.0.dist-info/RECORD
