Metadata-Version: 2.3
Name: cadence-example-plugins
Version: 1.3.0
Summary: Cadence Plugins - Collection of example AI agent plugins for Cadence AI Framework
License: MIT
Keywords: ai,agents,cadence-ai,plugins,cadence-plugins,langchain,langgraph,multi-agent
Author: Jonas Kahn
Author-email: me@ifelse.one
Requires-Python: >=3.13,<3.14
Classifier: Intended Audience :: Developers
Classifier: License :: OSI Approved :: MIT License
Classifier: Programming Language :: Python :: 3
Classifier: Programming Language :: Python :: 3.13
Classifier: Topic :: Software Development :: Libraries :: Python Modules
Classifier: Topic :: Scientific/Engineering :: Artificial Intelligence
Provides-Extra: dev
Requires-Dist: black (>=25.1.0,<26.0.0) ; extra == "dev"
Requires-Dist: cadence-sdk (>=1.3.0,<2.0.0)
Requires-Dist: ddgs (>=9.5.4,<10.0.0)
Requires-Dist: isort (>=6.0.1,<7.0.0) ; extra == "dev"
Requires-Dist: mypy (>=1.17.1,<2.0.0) ; extra == "dev"
Requires-Dist: pre-commit (>=4.3.0,<5.0.0) ; extra == "dev"
Requires-Dist: pydantic (>=2.11.7,<3.0.0)
Requires-Dist: pytest (>=8.4.1,<9.0.0) ; extra == "dev"
Requires-Dist: pytest-asyncio (>=1.1.0,<2.0.0) ; extra == "dev"
Requires-Dist: pytest-cov (>=6.2.1,<7.0.0) ; extra == "dev"
Requires-Dist: pytest-mock (>=3.14.1,<4.0.0) ; extra == "dev"
Requires-Dist: ruff (>=0.12.9,<0.13.0) ; extra == "dev"
Project-URL: Documentation, https://cadence-plugins.readthedocs.io/
Project-URL: Homepage, https://github.com/jonaskahn/cadence-plugins
Project-URL: Repository, https://github.com/jonaskahn/cadence-plugins.git
Project-URL: issues, https://github.com/jonaskahn/cadence-plugins/issues
